oracle_select/__init__.py
oracle_select/select.py
oracle_select-0.1.3.dist-info/METADATA
oracle_select-0.1.3.dist-info/WHEEL
oracle_select-0.1.3.dist-info/top_level.txt
oracle_select-0.1.3.dist-info/RECORD
