Metadata-Version: 2.1
Name: oracle-select
Version: 0.1.3
Summary: Easy interface for reading from Oracle databases
Home-page: UNKNOWN
Author: Jamie Davis
Author-email: jamjam@umich.edu
License: MIT
Keywords: oracle cx_Oracle
Platform: UNKNOWN
Classifier: Development Status :: 3 - Alpha
Classifier: License :: OSI Approved :: MIT License
Classifier: Programming Language :: Python :: 3.6
Requires-Dist: attrdict
Requires-Dist: cx-Oracle
Provides-Extra: utils
Requires-Dist: pandas ; extra == 'utils'
Requires-Dist: IPython ; extra == 'utils'
